[{"info":{"fromStation":"Gia Lâm","toStation":"Long Biên","name":"7902","type":"Tàu khách rỗng","date":"2018-11-28","departedTime":"2018-11-28T09:00:00.000Z","arriveTime":"1970-01-01T00:00:00.000Z","company":"FHN","status":1},"locomotive":[],"timetable":[]},{"info":{"fromStation":"Sài Gòn","toStation":"Hà Nội","name":"SE6","type":"Tàu khách TN","date":"2018-11-28","departedTime":"2018-11-28T02:00:00.000Z","arriveTime":"1970-01-01T00:00:00.000Z","company":"FHN","status":3},"locomotive":[],"timetable":[]},{"info":{"fromStation":"Gia Lâm","toStation":"Yên Viên","name":"0901","type":"Tàu đầu máy đơn","date":"2018-11-28","departedTime":"2018-11-28T01:43:00.000Z","arriveTime":"1970-01-01T00:00:00.000Z","company":"TCT","status":4},"locomotive":[{"type":"C","name":"D9E-216","fromStation":"Gia Lâm","toStation":"Gia Lâm","fromTime":"2018-11-28T01:43:00.000Z","toTime":"2018-11-28T01:43:00.000Z"}],"timetable":[{"station":"Gia Lâm","out":"2018-11-28T01:43:00.000Z"}]},{"info":{"fromStation":"Yên Viên","toStation":"Lào Cai","name":"2221","type":"Tàu hàng khu đoạn","date":"2018-11-28","departedTime":"2018-11-28T01:39:00.000Z","arriveTime":"1970-01-01T00:00:00.000Z","company":"FHN","status":4},"locomotive":[{"type":"C","name":"D19E-965","fromStation":"Yên Viên","toStation":"Yên Viên","fromTime":"2018-11-28T01:39:00.000Z","toTime":"2018-11-28T01:39:00.000Z"}],"timetable":[{"station":"Yên Viên","out":"2018-11-28T01:39:00.000Z"}]},{"info":{"fromStation":"Hải Phòng","toStation":"Long Biên","name":"LP6","type":"Tàu khách khu đoạn","date":"2018-11-28","departedTime":"2018-11-28T01:35:42.000Z","arriveTime":"1970-01-01T00:00:00.000Z","company":"FHN","status":1},"locomotive":[],"timetable":[]},{"info":{"fromStation":"Sóng Thần","toStation":"Giáp Bát","name":"AGS2","type":"Tàu hàng chuyên tuyến","date":"2018-11-28","departedTime":"2018-11-28T01:34:41.000Z","arriveTime":"1970-01-01T00:00:00.000Z","company":"FRA","status":1},"locomotive":[],"timetable":[]},{"info":{"fromStation":"Nha Trang","toStation":"Hòa Đa","name":"4584","type":"Tàu thoi nhiều khu gian, tàu công trình nhiều khu gian","date":"2018-11-28","departedTime":"2018-11-28T01:30:00.000Z","arriveTime":"1970-01-01T00:00:00.000Z","company":"FSG","status":1},"locomotive":[],"timetable":[]},{"info":{"fromStation":"Đà Nẵng","toStation":"Đồng Hới","name":"2416","type":"Tàu hàng khu đoạn","date":"2018-11-28","departedTime":"2018-11-28T01:20:36.000Z","arriveTime":"1970-01-01T00:00:00.000Z","company":"","status":3},"locomotive":[],"timetable":[]},{"info":{"fromStation":"Yên Viên","toStation":"Hải Phòng","name":"9110/3109","type":"Tàu thoi 1 khu gian, tàu công trình 1 khu gian","date":"2018-11-28","departedTime":"2018-11-28T01:20:00.000Z","arriveTime":"1970-01-01T00:00:00.000Z","company":"FHN","status":4},"locomotive":[{"type":"C","name":"D19E-980","fromStation":"Yên Viên","toStation":"Gia Lâm","fromTime":"2018-11-28T01:20:00.000Z","toTime":"2018-11-28T01:36:00.000Z"}],"timetable":[{"station":"Yên Viên","out":"2018-11-28T01:20:00.000Z"},{"station":"Gia Lâm","in":"2018-11-28T01:36:00.000Z","out":"2018-11-28T01:36:00.000Z"}]},{"info":{"fromStation":"Cầu Giát","toStation":"Mỹ Lý","name":"4371","type":"Tàu thoi nhiều khu gian, tàu công trình nhiều khu gian","date":"2018-11-28","departedTime":"2018-11-28T01:04:58.000Z","arriveTime":"1970-01-01T00:00:00.000Z","company":"FHN","status":4},"locomotive":[{"type":"C","name":"D9E-246","fromStation":"Cầu Giát","toStation":"Cầu Giát","fromTime":"2018-11-28T01:04:58.000Z","toTime":"2018-11-28T01:04:58.000Z"}],"timetable":[{"station":"Cầu Giát","out":"2018-11-28T01:04:58.000Z"}]},{"info":{"fromStation":"Giáp Bát","toStation":"Văn Điển","name":"9303","type":"Tàu thoi 1 khu gian, tàu công trình 1 khu gian","date":"2018-11-28","departedTime":"2018-11-28T01:02:00.000Z","arriveTime":"2018-11-28T01:12:00.000Z","company":"FHN","status":6},"locomotive":[{"type":"C","name":"D12E-645","fromStation":"Giáp Bát","toStation":"Văn Điển","fromTime":"2018-11-28T01:02:00.000Z","toTime":"2018-11-28T01:12:00.000Z"}],"timetable":[{"station":"Giáp Bát","out":"2018-11-28T01:02:00.000Z"},{"station":"Văn Điển","in":"2018-11-28T01:12:00.000Z"}]},{"info":{"fromStation":"Long Biên","toStation":"Gia Lâm","name":"7901","type":"Tàu khách rỗng","date":"2018-11-28","departedTime":"2018-11-28T01:00:00.000Z","arriveTime":"2018-11-28T01:08:00.000Z","company":"FHN","status":6},"locomotive":[{"type":"C","name":"D12E-655","fromStation":"Long Biên","toStation":"Gia Lâm","fromTime":"2018-11-28T01:00:00.000Z","toTime":"2018-11-28T01:08:00.000Z"},{"name":"D9E-216","fromStation":"Long Biên","toStation":"Gia Lâm","end":"Gia Lâm","fromId":3012,"toId":2968,"endId":2968,"type":"Ng","fromTime":"2018-11-28T01:00:00.000Z","toTime":"2018-11-28T01:08:00.000Z"}],"timetable":[{"station":"Long Biên","out":"2018-11-28T01:00:00.000Z"},{"station":"Gia Lâm","in":"2018-11-28T01:08:00.000Z"}]},{"info":{"fromStation":"Xuân Giao A","toStation":"Tiên Kiên","name":"2758","type":"Tàu hàng khu đoạn","date":"2018-11-28","departedTime":"2018-11-28T01:00:00.000Z","arriveTime":"1970-01-01T00:00:00.000Z","company":"FHN","status":4},"locomotive":[{"type":"C","name":"D10H-010","fromStation":"Xuân Giao A","toStation":"Phố Lu","fromTime":"2018-11-28T01:00:00.000Z","toTime":"2018-11-28T01:28:00.000Z"}],"timetable":[{"station":"Xuân Giao A","out":"2018-11-28T01:00:00.000Z"},{"station":"Phố Lu","in":"2018-11-28T01:28:00.000Z","out":"2018-11-28T01:28:00.000Z"}]},{"info":{"fromStation":"Lào Cai","toStation":"Sơn Yêu","name":"1213","type":"Tàu hàng LVQT","date":"2018-11-28","departedTime":"2018-11-28T00:54:42.000Z","arriveTime":"1970-01-01T00:00:00.000Z","company":"FHN","status":1},"locomotive":[],"timetable":[]},{"info":{"fromStation":"Ninh Bình","toStation":"Cầu Yên","name":"9311","type":"Tàu thoi 1 khu gian, tàu công trình 1 khu gian","date":"2018-11-28","departedTime":"2018-11-28T00:47:50.000Z","arriveTime":"1970-01-01T00:00:00.000Z","company":"FHN","status":3},"locomotive":[],"timetable":[]},{"info":{"fromStation":"Hải Phòng","toStation":"Hải Dương","name":"6102","type":"Tàu chạy thử","date":"2018-11-28","departedTime":"2018-11-28T00:46:48.000Z","arriveTime":"1970-01-01T00:00:00.000Z","company":"FHN","status":3},"locomotive":[],"timetable":[]},{"info":{"fromStation":"Sóng Thần","toStation":"Diêu Trì","name":"2536","type":"Tàu hàng khu đoạn","date":"2018-11-28","departedTime":"2018-11-28T00:45:00.000Z","arriveTime":"1970-01-01T00:00:00.000Z","company":"FSG","status":2},"locomotive":[{"type":"C","name":"D13E-711","fromStation":"Sóng Thần","toStation":"Hố Nai","fromTime":"2018-11-28T00:45:00.000Z","toTime":"2018-11-28T01:35:00.000Z"}],"timetable":[{"station":"Sóng Thần","out":"2018-11-28T00:45:00.000Z"},{"station":"Hố Nai","in":"2018-11-28T01:35:00.000Z"}]},{"info":{"fromStation":"Long Biên","toStation":"Đồng Đăng","name":"ÐÐ5","type":"Tàu khách khu đoạn","date":"2018-11-28","departedTime":"2018-11-28T00:16:00.000Z","arriveTime":"1970-01-01T00:00:00.000Z","company":"FHN","status":4},"locomotive":[{"type":"C","name":"D9E-235","fromStation":"Long Biên","toStation":"Yên Viên","fromTime":"2018-11-28T00:16:00.000Z","toTime":"2018-11-28T00:44:00.000Z"},{"name":"D12E-655","fromStation":"Long Biên","toStation":"Gia Lâm","end":"Gia Lâm","fromId":3012,"toId":2968,"endId":2968,"type":"Ng","fromTime":"2018-11-28T00:16:00.000Z","toTime":"2018-11-28T00:24:00.000Z"}],"timetable":[{"station":"Long Biên","out":"2018-11-28T00:16:00.000Z"},{"station":"Gia Lâm","in":"2018-11-28T00:24:00.000Z","out":"2018-11-28T00:34:00.000Z"},{"station":"Yên Viên","in":"2018-11-28T00:44:00.000Z","out":"2018-11-28T00:46:00.000Z"}]},{"info":{"fromStation":"Mạo Khê","toStation":"Lan Mẫu","name":"50502","type":"Tàu đầu máy đơn","date":"2018-11-28","departedTime":"2018-11-28T00:15:00.000Z","arriveTime":"1970-01-01T00:00:00.000Z","company":"FHN","status":4},"locomotive":[{"type":"C","name":"D19Er-2032","fromStation":"Mạo Khê","toStation":"Chí Linh","fromTime":"2018-11-28T00:15:00.000Z","toTime":"2018-11-28T01:00:26.000Z"}],"timetable":[{"station":"Mạo Khê","out":"2018-11-28T00:15:00.000Z"},{"station":"Chí Linh","in":"2018-11-28T01:00:26.000Z","out":"2018-11-28T01:00:26.000Z"}]},{"info":{"fromStation":"Đồng Mỏ","toStation":"Đồng Mỏ","name":"9001","type":"Tàu thoi 1 khu gian, tàu công trình 1 khu gian","date":"2018-11-28","departedTime":"2018-11-28T00:15:00.000Z","arriveTime":"2018-11-28T00:50:00.000Z","company":"FHN","status":6},"locomotive":[{"type":"C","name":"D19E-975","fromStation":"Đồng Mỏ","toStation":"Đồng Mỏ","fromTime":"2018-11-28T00:15:00.000Z","toTime":"2018-11-28T00:50:00.000Z"}],"timetable":[{"station":"Đồng Mỏ","out":"2018-11-28T00:15:00.000Z","in":"2018-11-28T00:50:00.000Z"}]},{"info":{"fromStation":"Hà Nội","toStation":"Sài Gòn","name":"SE3","type":"Tàu khách TN","date":"2018-11-28","departedTime":"2018-11-28T00:14:32.000Z","arriveTime":"1970-01-01T00:00:00.000Z","company":"FSG","status":1},"locomotive":[],"timetable":[]},{"info":{"fromStation":"Kim Liên","toStation":"Đà Nẵng","name":"0401","type":"Tàu đầu máy đơn","date":"2018-11-28","departedTime":"2018-11-28T00:07:00.000Z","arriveTime":"1970-01-01T00:00:00.000Z","company":"TCT","status":4},"locomotive":[{"type":"C","name":"D20E-001","fromStation":"Kim Liên","toStation":"Kim Liên","fromTime":"2018-11-28T00:07:00.000Z","toTime":"2018-11-28T00:07:00.000Z"}],"timetable":[{"station":"Kim Liên","out":"2018-11-28T00:07:00.000Z"}]},{"info":{"fromStation":"Huế","toStation":"Sài Gòn","name":"SE21","type":"Tàu khách khu đoạn","date":"2018-11-28","departedTime":"2018-11-28T00:00:00.000Z","arriveTime":"1970-01-01T00:00:00.000Z","company":"FSG","status":4},"locomotive":[{"type":"C","name":"D12E-652","fromStation":"Huế","toStation":"Huế","fromTime":"2018-11-28T00:00:00.000Z","toTime":"2018-11-28T00:00:00.000Z"}],"timetable":[{"station":"Huế","out":"2018-11-28T00:00:00.000Z"}]},{"info":{"fromStation":"Gia Lâm","toStation":"Long Biên","name":"7002","type":"Tàu khách rỗng","date":"2018-11-28","departedTime":"2018-11-27T23:45:00.000Z","arriveTime":"2018-11-27T23:55:00.000Z","company":"FHN","status":6},"locomotive":[{"type":"C","name":"D12E-655","fromStation":"Gia Lâm","toStation":"Long Biên","fromTime":"2018-11-27T23:45:00.000Z","toTime":"2018-11-27T23:55:00.000Z"},{"name":"D9E-235","fromStation":"Gia Lâm","toStation":"Long Biên","end":"Long Biên","fromId":2968,"toId":3012,"endId":3012,"type":"Ng","fromTime":"2018-11-27T23:45:00.000Z","toTime":"2018-11-27T23:55:00.000Z"}],"timetable":[{"station":"Gia Lâm","out":"2018-11-27T23:45:00.000Z"},{"station":"Long Biên","in":"2018-11-27T23:55:00.000Z"}]},{"info":{"fromStation":"Sài Gòn","toStation":"Phan Thiết","name":"SPT2","type":"Tàu khách khu đoạn","date":"2018-11-28","departedTime":"2018-11-27T23:40:00.000Z","arriveTime":"1970-01-01T00:00:00.000Z","company":"FSG","status":4},"locomotive":[{"type":"C","name":"D13E-708","fromStation":"Sài Gòn","toStation":"Trảng Bom","fromTime":"2018-11-27T23:40:00.000Z","toTime":"2018-11-28T01:18:00.000Z"}],"timetable":[{"station":"Sài Gòn","out":"2018-11-27T23:40:00.000Z"},{"station":"Sóng Thần","in":"2018-11-28T00:17:00.000Z","out":"2018-11-28T00:31:00.000Z"},{"station":"Hố Nai","in":"2018-11-28T01:09:00.000Z","out":"2018-11-28T01:09:00.000Z"},{"station":"Trảng Bom","in":"2018-11-28T01:18:00.000Z","out":"2018-11-28T01:18:00.000Z"}]},{"info":{"fromStation":"Lào Cai","toStation":"Hà Nội","name":"SP4","type":"Tàu khách khu đoạn","date":"2018-11-28","departedTime":"2018-11-27T23:10:25.000Z","arriveTime":"1970-01-01T00:00:00.000Z","company":"FHN","status":1},"locomotive":[],"timetable":[]},{"info":{"fromStation":"Hà Nội","toStation":"Yên Bái","name":"YB3","type":"Tàu khách khu đoạn","date":"2018-11-28","departedTime":"2018-11-27T23:10:00.000Z","arriveTime":"1970-01-01T00:00:00.000Z","company":"FHN","status":4},"locomotive":[{"type":"C","name":"D12E-636","fromStation":"Hà Nội","toStation":"Việt Trì","fromTime":"2018-11-27T23:10:00.000Z","toTime":"2018-11-28T01:29:00.000Z"}],"timetable":[{"station":"Hà Nội","out":"2018-11-27T23:10:00.000Z"},{"station":"Long Biên","in":"2018-11-27T23:18:00.000Z","out":"2018-11-27T23:21:00.000Z"},{"station":"Gia Lâm","in":"2018-11-27T23:29:00.000Z","out":"2018-11-27T23:32:00.000Z"},{"station":"Yên Viên","in":"2018-11-27T23:44:00.000Z","out":"2018-11-27T23:46:00.000Z"},{"station":"Đông Anh","in":"2018-11-28T00:16:00.000Z","out":"2018-11-28T00:18:00.000Z"},{"station":"Bắc Hồng","in":"2018-11-28T00:25:00.000Z","out":"2018-11-28T00:25:00.000Z"},{"station":"Phúc Yên","in":"2018-11-28T00:41:00.000Z","out":"2018-11-28T00:43:00.000Z"},{"station":"Hương Canh","in":"2018-11-28T00:54:00.000Z","out":"2018-11-28T00:54:00.000Z"},{"station":"Việt Trì","in":"2018-11-28T01:29:00.000Z","out":"2018-11-28T01:31:00.000Z"}]},{"info":{"fromStation":"Hải Phòng","toStation":"Long Biên","name":"LP2","type":"Tàu khách khu đoạn","date":"2018-11-28","departedTime":"2018-11-27T23:10:00.000Z","arriveTime":"2018-11-28T01:37:00.000Z","company":"FHN","status":6},"locomotive":[{"type":"C","name":"D12E-623","fromStation":"Hải Phòng","toStation":"Long Biên","fromTime":"2018-11-27T23:10:00.000Z","toTime":"2018-11-28T01:37:00.000Z"},{"name":"D12E-655","fromStation":"Gia Lâm","toStation":"Long Biên","end":"Long Biên","fromId":2968,"toId":3012,"endId":3012,"type":"Ng","fromTime":"2018-11-28T01:29:00.000Z","toTime":"2018-11-28T01:37:00.000Z"}],"timetable":[{"station":"Hải Phòng","out":"2018-11-27T23:10:00.000Z"},{"station":"Thượng Lý","in":"2018-11-27T23:20:00.000Z","out":"2018-11-27T23:22:00.000Z"},{"station":"Vật Cách","in":"2018-11-27T23:30:00.000Z","out":"2018-11-27T23:30:00.000Z"},{"station":"Gia Lâm","in":"2018-11-28T01:23:00.000Z","out":"2018-11-28T01:29:00.000Z"},{"station":"Long Biên","in":"2018-11-28T01:37:00.000Z"}]},{"info":{"fromStation":"Kim Liên","toStation":"Đà Nẵng","name":"0409","type":"Tàu đầu máy đơn","date":"2018-11-28","departedTime":"2018-11-27T23:05:00.000Z","arriveTime":"1970-01-01T00:00:00.000Z","company":"TCT","status":4},"locomotive":[{"type":"C","name":"D12E-635","fromStation":"Kim Liên","toStation":"Kim Liên","fromTime":"2018-11-27T23:05:00.000Z","toTime":"2018-11-27T23:05:00.000Z"}],"timetable":[{"station":"Kim Liên","out":"2018-11-27T23:05:00.000Z"}]},{"info":{"fromStation":"Sài Gòn","toStation":"Hà Nội","name":"SE8","type":"Tàu khách TN","date":"2018-11-28","departedTime":"2018-11-27T23:04:00.000Z","arriveTime":"1970-01-01T00:00:00.000Z","company":"FSG","status":4},"locomotive":[{"type":"C","name":"D19E-915","fromStation":"Sài Gòn","toStation":"Trảng Bom","fromTime":"2018-11-27T23:04:00.000Z","toTime":"2018-11-28T00:25:00.000Z"}],"timetable":[{"station":"Sài Gòn","out":"2018-11-27T23:04:00.000Z"},{"station":"Sóng Thần","in":"2018-11-27T23:32:00.000Z","out":"2018-11-27T23:32:00.000Z"},{"station":"Hố Nai","in":"2018-11-28T00:15:00.000Z","out":"2018-11-28T00:15:00.000Z"},{"station":"Trảng Bom","in":"2018-11-28T00:25:00.000Z","out":"2018-11-28T00:25:00.000Z"}]},{"info":{"fromStation":"Hà Nội","toStation":"Sài Gòn","name":"SE7","type":"Tàu khách TN","date":"2018-11-28","departedTime":"2018-11-27T23:00:00.000Z","arriveTime":"1970-01-01T00:00:00.000Z","company":"FSG","status":4},"locomotive":[{"type":"C","name":"D19E-926","fromStation":"Hà Nội","toStation":"Cầu Yên","fromTime":"2018-11-27T23:00:00.000Z","toTime":"2018-11-28T01:31:00.000Z"}],"timetable":[{"station":"Hà Nội","out":"2018-11-27T23:00:00.000Z"},{"station":"Giáp Bát","in":"2018-11-27T23:12:00.000Z","out":"2018-11-27T23:12:00.000Z"},{"station":"Văn Điển","in":"2018-11-27T23:16:00.000Z","out":"2018-11-27T23:16:00.000Z"},{"station":"Phủ Lý","in":"2018-11-28T00:03:00.000Z","out":"2018-11-28T00:06:00.000Z"},{"station":"Ninh Bình","in":"2018-11-28T01:21:00.000Z","out":"2018-11-28T01:24:00.000Z"},{"station":"Cầu Yên","in":"2018-11-28T01:31:00.000Z","out":"2018-11-28T01:31:00.000Z"}]},{"info":{"fromStation":"Hà Nội","toStation":"Hải Phòng","name":"HP1","type":"Tàu khách khu đoạn","date":"2018-11-28","departedTime":"2018-11-27T23:00:00.000Z","arriveTime":"2018-11-28T01:25:00.000Z","company":"FHN","status":6},"locomotive":[{"type":"C","name":"D12E-648","fromStation":"Hà Nội","toStation":"Hải Phòng","fromTime":"2018-11-27T23:00:00.000Z","toTime":"2018-11-28T01:25:00.000Z"}],"timetable":[{"station":"Hà Nội","out":"2018-11-27T23:00:00.000Z"},{"station":"Long Biên","in":"2018-11-27T23:07:00.000Z","out":"2018-11-27T23:07:00.000Z"},{"station":"Gia Lâm","in":"2018-11-27T23:14:00.000Z","out":"2018-11-27T23:16:00.000Z"},{"station":"Vật Cách","in":"2018-11-28T01:04:00.000Z","out":"2018-11-28T01:04:00.000Z"},{"station":"Thượng Lý","in":"2018-11-28T01:11:00.000Z","out":"2018-11-28T01:15:00.000Z"},{"station":"Hải Phòng","in":"2018-11-28T01:25:00.000Z"}]},{"info":{"fromStation":"Hà Nội","toStation":"Lào Cai","name":"SP3","type":"Tàu khách khu đoạn","date":"2018-11-28","departedTime":"2018-11-27T22:54:53.000Z","arriveTime":"1970-01-01T00:00:00.000Z","company":"FHN","status":1},"locomotive":[],"timetable":[]},{"info":{"fromStation":"Lâm Thao","toStation":"Xuân Giao A","name":"2739","type":"Tàu hàng khu đoạn","date":"2018-11-28","departedTime":"2018-11-27T22:52:04.000Z","arriveTime":"1970-01-01T00:00:00.000Z","company":"FHN","status":3},"locomotive":[],"timetable":[]},{"info":{"fromStation":"Gia Lâm","toStation":"Yên Viên","name":"50901","type":"Tàu đầu máy đơn","date":"2018-11-28","departedTime":"2018-11-27T22:40:00.000Z","arriveTime":"2018-11-27T22:48:00.000Z","company":"FHN","status":6},"locomotive":[{"type":"C","name":"D14Er-2013","fromStation":"Gia Lâm","toStation":"Yên Viên","fromTime":"2018-11-27T22:40:00.000Z","toTime":"2018-11-27T22:48:00.000Z"}],"timetable":[{"station":"Gia Lâm","out":"2018-11-27T22:40:00.000Z"},{"station":"Yên Viên","in":"2018-11-27T22:48:00.000Z"}]},{"info":{"fromStation":"Quán Triều","toStation":"Long Biên","name":"QT2","type":"Tàu khách khu đoạn","date":"2018-11-28","departedTime":"2018-11-27T22:40:00.000Z","arriveTime":"2018-11-28T00:48:00.000Z","company":"FHN","status":6},"locomotive":[{"type":"C","name":"D9E-216","fromStation":"Quán Triều","toStation":"Long Biên","fromTime":"2018-11-27T22:40:00.000Z","toTime":"2018-11-28T00:47:00.000Z"},{"name":"D12E-655","fromStation":"Gia Lâm","toStation":"Long Biên","end":"Long Biên","fromId":2968,"toId":3012,"endId":3012,"type":"Ng","fromTime":"2018-11-28T00:39:00.000Z","toTime":"2018-11-28T00:47:00.000Z"}],"timetable":[{"station":"Quán Triều","out":"2018-11-27T22:40:00.000Z"},{"station":"Lưu Xá","in":"2018-11-27T22:58:00.000Z","out":"2018-11-27T23:00:00.000Z"},{"station":"Đông Anh","in":"2018-11-28T00:00:00.000Z","out":"2018-11-28T00:02:00.000Z"},{"station":"Yên Viên","in":"2018-11-28T00:20:00.000Z","out":"2018-11-28T00:22:00.000Z"},{"station":"Gia Lâm","in":"2018-11-28T00:32:00.000Z","out":"2018-11-28T00:39:00.000Z"},{"station":"Long Biên","in":"2018-11-28T00:47:00.000Z"}]},{"info":{"fromStation":"Lào Cai","toStation":"Hà Nội","name":"SP2","type":"Tàu khách khu đoạn","date":"2018-11-28","departedTime":"2018-11-27T22:32:38.000Z","arriveTime":"1970-01-01T00:00:00.000Z","company":"FHN","status":1},"locomotive":[],"timetable":[]},{"info":{"fromStation":"Xuân Giao A","toStation":"Tiên Kiên","name":"2756","type":"Tàu hàng khu đoạn","date":"2018-11-28","departedTime":"2018-11-27T22:20:00.000Z","arriveTime":"1970-01-01T00:00:00.000Z","company":"FHN","status":4},"locomotive":[{"type":"C","name":"D10H-029","fromStation":"Xuân Giao A","toStation":"Lâm Giang","fromTime":"2018-11-27T22:20:00.000Z","toTime":"2018-11-28T00:48:00.000Z"}],"timetable":[{"station":"Xuân Giao A","out":"2018-11-27T22:20:00.000Z"},{"station":"Phố Lu","in":"2018-11-27T22:50:00.000Z","out":"2018-11-27T22:50:00.000Z"},{"station":"Lâm Giang","in":"2018-11-28T00:48:00.000Z","out":"2018-11-28T00:48:00.000Z"}]},{"info":{"fromStation":"Đà Nẵng","toStation":"Kim Liên","name":"0412","type":"Tàu đầu máy đơn","date":"2018-11-28","departedTime":"2018-11-27T22:07:00.000Z","arriveTime":"2018-11-27T23:00:00.000Z","company":"TCT","status":6},"locomotive":[{"type":"C","name":"D18E-608","fromStation":"Đà Nẵng","toStation":"Kim Liên","fromTime":"2018-11-27T22:07:00.000Z","toTime":"2018-11-27T23:00:00.000Z"}],"timetable":[{"station":"Đà Nẵng","out":"2018-11-27T22:07:00.000Z"},{"station":"Kim Liên","in":"2018-11-27T23:00:00.000Z"}]},{"info":{"fromStation":"Yên Viên","toStation":"Lào Cai","name":"2213","type":"Tàu hàng khu đoạn","date":"2018-11-28","departedTime":"2018-11-27T22:05:00.000Z","arriveTime":"1970-01-01T00:00:00.000Z","company":"FHN","status":3},"locomotive":[{"type":"C","name":"D19E-979","fromStation":"Yên Viên","toStation":"Việt Trì","fromTime":"2018-11-27T22:05:00.000Z","toTime":"2018-11-28T00:26:00.000Z"},{"name":"D10H-003","fromStation":"Việt Trì","toStation":"Tiên Kiên","end":"Tiên Kiên","fromId":3097,"toId":3082,"endId":3082,"type":"Ng","fromTime":null}],"timetable":[{"station":"Yên Viên","out":"2018-11-27T22:05:00.000Z"},{"station":"Đông Anh","in":"2018-11-27T22:29:00.000Z","out":"2018-11-27T22:29:00.000Z"},{"station":"Bắc Hồng","in":"2018-11-27T22:41:00.000Z","out":"2018-11-27T23:00:00.000Z"},{"station":"Phúc Yên","in":"2018-11-27T23:23:00.000Z","out":"2018-11-27T23:23:00.000Z"},{"station":"Hương Canh","in":"2018-11-27T23:37:00.000Z","out":"2018-11-27T23:37:00.000Z"},{"station":"Việt Trì","in":"2018-11-28T00:26:00.000Z"}]},{"info":{"fromStation":"Yên Viên","toStation":"Hạ Long","name":"51501","type":"Tàu hỗn hợp, quân dụng, chở công nhân","date":"2018-11-28","departedTime":"2018-11-27T21:55:00.000Z","arriveTime":"1970-01-01T00:00:00.000Z","company":"FHN","status":4},"locomotive":[{"type":"C","name":"D14Er-2014","fromStation":"Yên Viên","toStation":"Kép","fromTime":"2018-11-27T21:55:00.000Z","toTime":"2018-11-27T23:50:00.000Z"}],"timetable":[{"station":"Yên Viên","out":"2018-11-27T21:55:00.000Z"},{"station":"Bắc Giang","in":"2018-11-27T23:11:00.000Z","out":"2018-11-27T23:14:00.000Z"},{"station":"Kép","in":"2018-11-27T23:50:00.000Z","out":"2018-11-28T00:16:00.000Z"}]},{"info":{"fromStation":"Hà Nội","toStation":"Vinh","name":"NA1","type":"Tàu khách khu đoạn","date":"2018-11-28","departedTime":"2018-11-27T21:46:44.000Z","arriveTime":"1970-01-01T00:00:00.000Z","company":"FHN","status":1},"locomotive":[],"timetable":[]},{"info":{"fromStation":"Yên Viên","toStation":"Gia Lâm","name":"0906","type":"Tàu đầu máy đơn","date":"2018-11-28","departedTime":"2018-11-27T21:45:00.000Z","arriveTime":"2018-11-27T21:55:00.000Z","company":"TCT","status":6},"locomotive":[{"type":"C","name":"D12E-655","fromStation":"Yên Viên","toStation":"Gia Lâm","fromTime":"2018-11-27T21:45:00.000Z","toTime":"2018-11-27T21:55:00.000Z"}],"timetable":[{"station":"Yên Viên","out":"2018-11-27T21:45:00.000Z"},{"station":"Gia Lâm","in":"2018-11-27T21:55:00.000Z"}]},{"info":{"fromStation":"Hà Nội","toStation":"Lào Cai","name":"SP1","type":"Tàu khách khu đoạn","date":"2018-11-28","departedTime":"2018-11-27T21:41:20.000Z","arriveTime":"1970-01-01T00:00:00.000Z","company":"FHN","status":1},"locomotive":[],"timetable":[]},{"info":{"fromStation":"Giáp Bát","toStation":"Tiên Kiên","name":"3603","type":"Tàu hàng khu đoạn, đường ngắn, bất thường","date":"2018-11-28","departedTime":"2018-11-27T21:38:00.000Z","arriveTime":"1970-01-01T00:00:00.000Z","company":"FHN","status":3},"locomotive":[{"type":"C","name":"D10H-025","fromStation":"Giáp Bát","toStation":"Phúc Yên","fromTime":"2018-11-27T21:38:00.000Z","toTime":"2018-11-28T00:27:00.000Z"}],"timetable":[{"station":"Giáp Bát","out":"2018-11-27T21:38:00.000Z"},{"station":"Văn Điển","in":"2018-11-27T21:48:00.000Z","out":"2018-11-27T21:48:00.000Z"},{"station":"Hà Đông","in":"2018-11-27T22:13:00.000Z","out":"2018-11-27T22:35:00.000Z"},{"station":"Phú Diễn","in":"2018-11-27T22:36:00.000Z","out":"2018-11-27T22:38:00.000Z"},{"station":"Bắc Hồng","in":"2018-11-28T00:04:00.000Z","out":"2018-11-28T00:04:00.000Z"},{"station":"Phúc Yên","in":"2018-11-28T00:27:00.000Z"}]},{"info":{"fromStation":"Đà Nẵng","toStation":"Kim Liên","name":"0410","type":"Tàu đầu máy đơn","date":"2018-11-28","departedTime":"2018-11-27T21:37:00.000Z","arriveTime":"2018-11-27T22:15:00.000Z","company":"TCT","status":6},"locomotive":[{"type":"C","name":"D11H-347","fromStation":"Đà Nẵng","toStation":"Kim Liên","fromTime":"2018-11-27T21:37:00.000Z","toTime":"2018-11-27T22:15:00.000Z"}],"timetable":[{"station":"Đà Nẵng","out":"2018-11-27T21:37:00.000Z"},{"station":"Kim Liên","in":"2018-11-27T22:15:00.000Z"}]},{"info":{"fromStation":"Hà Nội","toStation":"Sài Gòn","name":"SE9","type":"Tàu khách TN","date":"2018-11-28","departedTime":"2018-11-27T21:25:57.000Z","arriveTime":"1970-01-01T00:00:00.000Z","company":"FSG","status":1},"locomotive":[],"timetable":[]},{"info":{"fromStation":"Kim Liên","toStation":"Đà Nẵng","name":"0407","type":"Tàu đầu máy đơn","date":"2018-11-28","departedTime":"2018-11-27T21:19:00.000Z","arriveTime":"2018-11-27T22:05:00.000Z","company":"TCT","status":6},"locomotive":[{"type":"C","name":"D11H-326","fromStation":"Kim Liên","toStation":"Đà Nẵng","fromTime":"2018-11-27T21:19:00.000Z","toTime":"2018-11-27T22:05:00.000Z"}],"timetable":[{"station":"Kim Liên","out":"2018-11-27T21:19:00.000Z"},{"station":"Đà Nẵng","in":"2018-11-27T22:05:00.000Z"}]},{"info":{"fromStation":"Yên Viên","toStation":"Gia Lâm","name":"0904","type":"Tàu đầu máy đơn","date":"2018-11-28","departedTime":"2018-11-27T21:18:00.000Z","arriveTime":"2018-11-27T21:29:00.000Z","company":"TCT","status":6},"locomotive":[{"type":"C","name":"D9E-235","fromStation":"Yên Viên","toStation":"Gia Lâm","fromTime":"2018-11-27T21:18:00.000Z","toTime":"2018-11-27T21:29:00.000Z"}],"timetable":[{"station":"Yên Viên","out":"2018-11-27T21:18:00.000Z"},{"station":"Gia Lâm","in":"2018-11-27T21:29:00.000Z"}]},{"info":{"fromStation":"Đồng Đăng","toStation":"Na Dương","name":"4050/4051","type":"Tàu thoi nhiều khu gian, tàu công trình nhiều khu gian","date":"2018-11-28","departedTime":"2018-11-27T21:00:00.000Z","arriveTime":"2018-11-28T00:30:26.000Z","company":"FHN","status":6},"locomotive":[{"type":"C","name":"D9E-241","fromStation":"Đồng Đăng","toStation":"Na Dương","fromTime":"2018-11-27T21:00:00.000Z","toTime":"2018-11-28T00:30:26.000Z"}],"timetable":[{"station":"Đồng Đăng","out":"2018-11-27T21:00:00.000Z"},{"station":"Lạng Sơn","in":"2018-11-27T21:30:00.000Z","out":"2018-11-27T21:30:00.000Z"},{"station":"Yên Trạch","in":"2018-11-27T21:40:54.000Z","out":"2018-11-27T22:27:02.000Z"},{"station":"Na Dương","in":"2018-11-28T00:30:26.000Z"}]},{"info":{"fromStation":"Cổ Thành","toStation":"Mạo Khê","name":"54551","type":"Tàu thoi nhiều khu gian, tàu công trình nhiều khu gian","date":"2018-11-28","departedTime":"2018-11-27T21:00:00.000Z","arriveTime":"2018-11-27T22:28:00.000Z","company":"FHN","status":6},"locomotive":[{"type":"C","name":"D19Er-2032","fromStation":"Cổ Thành","toStation":"Mạo Khê","fromTime":"2018-11-27T21:00:00.000Z","toTime":"2018-11-27T22:28:00.000Z"}],"timetable":[{"station":"Cổ Thành","out":"2018-11-27T21:00:00.000Z"},{"station":"Chí Linh","in":"2018-11-27T21:45:42.000Z","out":"2018-11-27T21:45:42.000Z"},{"station":"Mạo Khê","in":"2018-11-27T22:28:00.000Z"}]},{"info":{"fromStation":"Sóng Thần","toStation":"Sài Gòn","name":"0501","type":"Tàu đầu máy đơn","date":"2018-11-28","departedTime":"2018-11-27T20:56:59.000Z","arriveTime":"2018-11-27T22:00:00.000Z","company":"TCT","status":6},"locomotive":[{"type":"C","name":"D19E-952","fromStation":"Sóng Thần","toStation":"Sài Gòn","fromTime":"2018-11-27T20:56:59.000Z","toTime":"2018-11-27T22:00:00.000Z"}],"timetable":[{"station":"Sóng Thần","out":"2018-11-27T20:56:59.000Z"},{"station":"Sài Gòn","in":"2018-11-27T22:00:00.000Z"}]},{"info":{"fromStation":"Lâm Thao","toStation":"Giáp Bát","name":"3632","type":"Tàu hàng khu đoạn, đường ngắn, bất thường","date":"2018-11-28","departedTime":"2018-11-27T20:32:00.000Z","arriveTime":"1970-01-01T00:00:00.000Z","company":"FHN","status":4},"locomotive":[{"type":"C","name":"D10H-020","fromStation":"Lâm Thao","toStation":"Việt Trì","fromTime":"2018-11-27T20:32:00.000Z","toTime":"2018-11-27T22:53:00.000Z"}],"timetable":[{"station":"Lâm Thao","out":"2018-11-27T20:32:00.000Z"},{"station":"Tiên Kiên","in":"2018-11-27T20:44:00.000Z","out":"2018-11-27T22:00:00.000Z"},{"station":"Việt Trì","in":"2018-11-27T22:53:00.000Z","out":"2018-11-27T23:32:00.000Z"}]},{"info":{"fromStation":"Tiên Kiên","toStation":"Yên Viên","name":"3202","type":"Tàu hàng khu đoạn, đường ngắn, bất thường","date":"2018-11-28","departedTime":"2018-11-27T20:26:00.000Z","arriveTime":"2018-11-27T23:32:00.000Z","company":"FHN","status":6},"locomotive":[{"type":"C","name":"D19E-980","fromStation":"Tiên Kiên","toStation":"Yên Viên","fromTime":"2018-11-27T20:26:00.000Z","toTime":"2018-11-27T23:32:00.000Z"}],"timetable":[{"station":"Tiên Kiên","out":"2018-11-27T20:26:00.000Z"},{"station":"Việt Trì","in":"2018-11-27T21:01:00.000Z","out":"2018-11-27T21:01:00.000Z"},{"station":"Hương Canh","in":"2018-11-27T22:16:00.000Z","out":"2018-11-27T22:16:00.000Z"},{"station":"Phúc Yên","in":"2018-11-27T22:33:00.000Z","out":"2018-11-27T22:33:00.000Z"},{"station":"Bắc Hồng","in":"2018-11-27T22:57:00.000Z","out":"2018-11-27T22:57:00.000Z"},{"station":"Đông Anh","in":"2018-11-27T23:08:00.000Z","out":"2018-11-27T23:08:00.000Z"},{"station":"Yên Viên","in":"2018-11-27T23:32:00.000Z"}]},{"info":{"fromStation":"Kim Liên","toStation":"Đà Nẵng","name":"0405","type":"Tàu đầu máy đơn","date":"2018-11-28","departedTime":"2018-11-27T20:23:00.000Z","arriveTime":"2018-11-27T21:14:00.000Z","company":"TCT","status":6},"locomotive":[{"type":"C","name":"D19E-966","fromStation":"Kim Liên","toStation":"Đà Nẵng","fromTime":"2018-11-27T20:23:00.000Z","toTime":"2018-11-27T21:14:00.000Z"}],"timetable":[{"station":"Kim Liên","out":"2018-11-27T20:23:00.000Z"},{"station":"Đà Nẵng","in":"2018-11-27T21:14:00.000Z"}]},{"info":{"fromStation":"Yên Viên","toStation":"Đồng Đăng","name":"2001","type":"Tàu hàng khu đoạn","date":"2018-11-28","departedTime":"2018-11-27T20:10:00.000Z","arriveTime":"1970-01-01T00:00:00.000Z","company":"FHN","status":3},"locomotive":[{"type":"C","name":"D19E-977","fromStation":"Yên Viên","toStation":"Bắc Giang","fromTime":"2018-11-27T20:10:00.000Z","toTime":"2018-11-27T22:35:00.000Z"}],"timetable":[{"station":"Yên Viên","out":"2018-11-27T20:10:00.000Z"},{"station":"Sen Hồ","in":"2018-11-27T20:11:00.000Z","out":"2018-11-27T20:13:00.000Z"},{"station":"Bắc Giang","in":"2018-11-27T22:35:00.000Z"}]},{"info":{"fromStation":"Giáp Bát","toStation":"Sóng Thần","name":"ASY1","type":"Tàu hàng chuyên tuyến","date":"2018-11-28","departedTime":"2018-11-27T20:05:00.000Z","arriveTime":"1970-01-01T00:00:00.000Z","company":"FRA","status":4},"locomotive":[{"type":"C","name":"D13E-716","fromStation":"Giáp Bát","toStation":"Bỉm Sơn","fromTime":"2018-11-27T20:05:00.000Z","toTime":"2018-11-28T00:49:00.000Z"}],"timetable":[{"station":"Giáp Bát","out":"2018-11-27T20:05:00.000Z"},{"station":"Văn Điển","in":"2018-11-27T20:15:00.000Z","out":"2018-11-27T20:15:00.000Z"},{"station":"Phủ Lý","in":"2018-11-27T22:05:00.000Z","out":"2018-11-27T22:05:00.000Z"},{"station":"Ninh Bình","in":"2018-11-27T23:53:00.000Z","out":"2018-11-27T23:53:00.000Z"},{"station":"Cầu Yên","in":"2018-11-28T00:00:00.000Z","out":"2018-11-28T00:00:00.000Z"},{"station":"Bỉm Sơn","in":"2018-11-28T00:49:00.000Z","out":"2018-11-28T00:49:00.000Z"}]},{"info":{"fromStation":"Đồng Đăng","toStation":"Bằng Tường","name":"T8702","type":"Tàu khách LVQT","date":"2018-11-28","departedTime":"2018-11-27T19:50:00.000Z","arriveTime":"2018-11-27T20:30:00.000Z","company":"FHN","status":6},"locomotive":[{"type":"C","name":"DETQ-0578","fromStation":"Đồng Đăng","toStation":"Bằng Tường","fromTime":"2018-11-27T19:50:00.000Z","toTime":"2018-11-27T20:30:00.000Z"}],"timetable":[{"station":"Đồng Đăng","out":"2018-11-27T19:50:00.000Z"},{"station":"Bằng Tường","in":"2018-11-27T20:30:00.000Z"}]},{"info":{"fromStation":"Sóng Thần","toStation":"Giáp Bát","name":"ASY2","type":"Tàu hàng chuyên tuyến","date":"2018-11-28","departedTime":"2018-11-27T19:45:00.000Z","arriveTime":"1970-01-01T00:00:00.000Z","company":"FRA","status":4},"locomotive":[{"type":"C","name":"D19E-959","fromStation":"Sóng Thần","toStation":"Trảng Bom","fromTime":"2018-11-27T19:45:00.000Z","toTime":"2018-11-27T22:05:00.000Z"}],"timetable":[{"station":"Sóng Thần","out":"2018-11-27T19:45:00.000Z"},{"station":"Hố Nai","in":"2018-11-27T20:57:00.000Z","out":"2018-11-27T22:04:00.000Z"},{"station":"Trảng Bom","in":"2018-11-27T22:05:00.000Z","out":"2018-11-27T23:37:00.000Z"}]},{"info":{"fromStation":"Yên Viên","toStation":"Lào Cai","name":"A2201","type":"Tàu hàng khu đoạn","date":"2018-11-28","departedTime":"2018-11-27T19:40:00.000Z","arriveTime":"1970-01-01T00:00:00.000Z","company":"FRA","status":4},"locomotive":[{"type":"C","name":"D19E-976","fromStation":"Yên Viên","toStation":"Tiên Kiên","fromTime":"2018-11-27T19:40:00.000Z","toTime":"2018-11-27T23:55:00.000Z"},{"name":"D10H-023","fromStation":"Yên Viên","toStation":"Việt Trì","end":"Tiên Kiên","fromId":3112,"toId":3097,"endId":3082,"type":"Ng","fromTime":"2018-11-27T19:40:00.000Z","toTime":"2018-11-27T22:46:00.000Z"}],"timetable":[{"station":"Yên Viên","out":"2018-11-27T19:40:00.000Z"},{"station":"Đông Anh","in":"2018-11-27T20:03:00.000Z","out":"2018-11-27T20:03:00.000Z"},{"station":"Bắc Hồng","in":"2018-11-27T20:18:00.000Z","out":"2018-11-27T20:42:00.000Z"},{"station":"Phúc Yên","in":"2018-11-27T21:10:00.000Z","out":"2018-11-27T21:23:00.000Z"},{"station":"Hương Canh","in":"2018-11-27T21:45:00.000Z","out":"2018-11-27T21:45:00.000Z"},{"station":"Việt Trì","in":"2018-11-27T22:46:00.000Z","out":"2018-11-27T23:10:00.000Z"},{"station":"Tiên Kiên","in":"2018-11-27T23:55:00.000Z","out":"2018-11-28T00:08:00.000Z"}]},{"info":{"fromStation":"Đà Nẵng","toStation":"Kim Liên","name":"0408","type":"Tàu đầu máy đơn","date":"2018-11-28","departedTime":"2018-11-27T19:25:00.000Z","arriveTime":"2018-11-27T19:45:00.000Z","company":"TCT","status":6},"locomotive":[{"type":"C","name":"D18E-607","fromStation":"Đà Nẵng","toStation":"Kim Liên","fromTime":"2018-11-27T19:25:00.000Z","toTime":"2018-11-27T19:45:00.000Z"}],"timetable":[{"station":"Đà Nẵng","out":"2018-11-27T19:25:00.000Z"},{"station":"Kim Liên","in":"2018-11-27T19:45:00.000Z"}]},{"info":{"fromStation":"Đồng Đăng","toStation":"Yên Viên","name":"2002","type":"Tàu hàng khu đoạn","date":"2018-11-28","departedTime":"2018-11-27T19:20:00.000Z","arriveTime":"1970-01-01T00:00:00.000Z","company":"FHN","status":4},"locomotive":[{"type":"C","name":"D19E-975","fromStation":"Đồng Đăng","toStation":"Đồng Mỏ","fromTime":"2018-11-27T19:20:00.000Z","toTime":"2018-11-28T00:05:00.000Z"}],"timetable":[{"station":"Đồng Đăng","out":"2018-11-27T19:20:00.000Z"},{"station":"Lạng Sơn","in":"2018-11-27T19:47:00.000Z","out":"2018-11-27T22:02:00.000Z"},{"station":"Yên Trạch","in":"2018-11-27T22:22:35.000Z","out":"2018-11-27T23:02:17.000Z"},{"station":"Đồng Mỏ","in":"2018-11-28T00:05:00.000Z","out":"2018-11-28T01:30:00.000Z"}]},{"info":{"fromStation":"Kim Liên","toStation":"Đà Nẵng","name":"4401","type":"Tàu thoi nhiều khu gian, tàu công trình nhiều khu gian","date":"2018-11-28","departedTime":"2018-11-27T19:11:00.000Z","arriveTime":"2018-11-27T19:40:00.000Z","company":"","status":6},"locomotive":[{"type":"C","name":"D18E-613","fromStation":"Kim Liên","toStation":"Đà Nẵng","fromTime":"2018-11-27T19:11:00.000Z","toTime":"2018-11-27T19:40:00.000Z"}],"timetable":[{"station":"Kim Liên","out":"2018-11-27T19:11:00.000Z"},{"station":"Đà Nẵng","in":"2018-11-27T19:40:00.000Z"}]},{"info":{"fromStation":"Văn Điển","toStation":"Giáp Bát","name":"9302","type":"Tàu thoi 1 khu gian, tàu công trình 1 khu gian","date":"2018-11-28","departedTime":"2018-11-27T19:07:00.000Z","arriveTime":"2018-11-27T19:20:00.000Z","company":"FHN","status":6},"locomotive":[{"type":"C","name":"D12E-645","fromStation":"Văn Điển","toStation":"Giáp Bát","fromTime":"2018-11-27T19:07:00.000Z","toTime":"2018-11-27T19:20:00.000Z"}],"timetable":[{"station":"Văn Điển","out":"2018-11-27T19:07:00.000Z"},{"station":"Giáp Bát","in":"2018-11-27T19:20:00.000Z"}]},{"info":{"fromStation":"Đồng Hới","toStation":"Đà Nẵng","name":"2411","type":"Tàu hàng khu đoạn","date":"2018-11-28","departedTime":"2018-11-27T18:57:00.000Z","arriveTime":"1970-01-01T00:00:00.000Z","company":"","status":2},"locomotive":[{"type":"C","name":"D11H-356","fromStation":"Đồng Hới","toStation":"Huế","fromTime":"2018-11-27T18:57:00.000Z","toTime":"2018-11-28T00:42:00.000Z"}],"timetable":[{"station":"Đồng Hới","out":"2018-11-27T18:57:00.000Z"},{"station":"Mỹ Đức","in":"2018-11-27T20:03:00.000Z","out":"2018-11-27T20:09:00.000Z"},{"station":"Đông Hà","in":"2018-11-27T22:41:00.000Z","out":"2018-11-27T22:41:00.000Z"},{"station":"Phò Trạch","in":"2018-11-27T23:36:00.000Z","out":"2018-11-27T23:36:00.000Z"},{"station":"Huế","in":"2018-11-28T00:42:00.000Z"}]},{"info":{"fromStation":"Đồng Đăng","toStation":"Gia Lâm","name":"MR2","type":"Tàu khách LVQT","date":"2018-11-28","departedTime":"2018-11-27T18:55:00.000Z","arriveTime":"2018-11-27T22:30:00.000Z","company":"FHN","status":6},"locomotive":[{"type":"C","name":"D14Er-2013","fromStation":"Đồng Đăng","toStation":"Gia Lâm","fromTime":"2018-11-27T18:55:00.000Z","toTime":"2018-11-27T22:30:00.000Z"}],"timetable":[{"station":"Đồng Đăng","out":"2018-11-27T18:55:00.000Z"},{"station":"Lạng Sơn","in":"2018-11-27T19:14:00.000Z","out":"2018-11-27T19:14:00.000Z"},{"station":"Yên Trạch","in":"2018-11-27T19:22:51.000Z","out":"2018-11-27T19:22:51.000Z"},{"station":"Đồng Mỏ","in":"2018-11-27T20:01:27.000Z","out":"2018-11-27T20:01:27.000Z"},{"station":"Kép","in":"2018-11-27T21:13:48.000Z","out":"2018-11-27T21:13:48.000Z"},{"station":"Bắc Giang","in":"2018-11-27T21:33:04.000Z","out":"2018-11-27T21:36:26.000Z"},{"station":"Yên Viên","in":"2018-11-27T22:19:00.000Z","out":"2018-11-27T22:20:00.000Z"},{"station":"Gia Lâm","in":"2018-11-27T22:30:00.000Z"}]},{"info":{"fromStation":"Giáp Bát","toStation":"Vinh","name":"2313","type":"Tàu hàng khu đoạn","date":"2018-11-28","departedTime":"2018-11-27T18:50:00.000Z","arriveTime":"1970-01-01T00:00:00.000Z","company":"FHN","status":4},"locomotive":[{"type":"C","name":"D13E-725","fromStation":"Giáp Bát","toStation":"Ninh Bình","fromTime":"2018-11-27T18:50:00.000Z","toTime":"2018-11-27T23:37:00.000Z"},{"name":"D12E-650","fromStation":"Ninh Bình","toStation":"Bỉm Sơn","end":"Bỉm Sơn","fromId":3035,"toId":2924,"endId":2924,"type":"N","fromTime":"2018-11-28T01:34:00.000Z"}],"timetable":[{"station":"Giáp Bát","out":"2018-11-27T18:50:00.000Z"},{"station":"Văn Điển","in":"2018-11-27T19:04:00.000Z","out":"2018-11-27T19:04:00.000Z"},{"station":"Phủ Lý","in":"2018-11-27T21:43:00.000Z","out":"2018-11-27T21:43:00.000Z"},{"station":"Ninh Bình","in":"2018-11-27T23:37:00.000Z","out":"2018-11-28T01:34:00.000Z"}]},{"info":{"fromStation":"Xuân Giao A","toStation":"Tiên Kiên","name":"2750","type":"Tàu hàng khu đoạn","date":"2018-11-28","departedTime":"2018-11-27T18:39:00.000Z","arriveTime":"1970-01-01T00:00:00.000Z","company":"FHN","status":4},"locomotive":[{"type":"C","name":"D10H-014","fromStation":"Xuân Giao A","toStation":"Văn Phú","fromTime":"2018-11-27T18:39:00.000Z","toTime":"2018-11-28T01:15:00.000Z"}],"timetable":[{"station":"Xuân Giao A","out":"2018-11-27T18:39:00.000Z"},{"station":"Phố Lu","in":"2018-11-27T19:05:00.000Z","out":"2018-11-27T19:35:00.000Z"},{"station":"Lâm Giang","in":"2018-11-27T22:37:00.000Z","out":"2018-11-27T22:37:00.000Z"},{"station":"Yên Bái","in":"2018-11-28T00:40:00.000Z","out":"2018-11-28T01:00:00.000Z"},{"station":"Văn Phú","in":"2018-11-28T01:15:00.000Z","out":"2018-11-28T01:15:00.000Z"}]},{"info":{"fromStation":"Lạc Đạo","toStation":"Yên Viên","name":"0104","type":"Tàu đầu máy đơn","date":"2018-11-28","departedTime":"2018-11-27T18:36:21.000Z","arriveTime":"2018-11-27T19:37:00.000Z","company":"TCT","status":6},"locomotive":[{"type":"C","name":"D9E-233","fromStation":"Lạc Đạo","toStation":"Yên Viên","fromTime":"2018-11-27T18:36:21.000Z","toTime":"2018-11-27T19:37:00.000Z"}],"timetable":[{"station":"Lạc Đạo","out":"2018-11-27T18:36:21.000Z"},{"station":"Gia Lâm","in":"2018-11-27T19:28:00.000Z","out":"2018-11-27T19:28:00.000Z"},{"station":"Yên Viên","in":"2018-11-27T19:37:00.000Z"}]},{"info":{"fromStation":"Tiên Kiên","toStation":"Xuân Giao A","name":"2705","type":"Tàu hàng khu đoạn","date":"2018-11-28","departedTime":"2018-11-27T18:08:00.000Z","arriveTime":"1970-01-01T00:00:00.000Z","company":"FHN","status":4},"locomotive":[{"type":"C","name":"D10H-016","fromStation":"Tiên Kiên","toStation":"Yên Bái","fromTime":"2018-11-27T18:08:00.000Z","toTime":"2018-11-27T21:17:00.000Z"},{"type":"C","name":"D10H-024","fromStation":"Yên Bái","toStation":"Lâm Giang","fromTime":"2018-11-27T22:06:00.000Z","toTime":"2018-11-28T00:23:00.000Z"},{"name":"D10H-007","fromStation":"Yên Bái","toStation":"Lâm Giang","end":"Lâm Giang","fromId":3104,"toId":2999,"endId":2999,"type":"Ng","fromTime":"2018-11-27T22:06:00.000Z","toTime":"2018-11-28T00:23:00.000Z"}],"timetable":[{"station":"Tiên Kiên","out":"2018-11-27T18:08:00.000Z"},{"station":"Văn Phú","in":"2018-11-27T21:00:00.000Z","out":"2018-11-27T21:00:00.000Z"},{"station":"Yên Bái","in":"2018-11-27T21:17:00.000Z","out":"2018-11-27T22:06:00.000Z"},{"station":"Lâm Giang","in":"2018-11-28T00:23:00.000Z","out":"2018-11-28T00:53:00.000Z"}]},{"info":{"fromStation":"Đà Nẵng","toStation":"Kim Liên","name":"0406","type":"Tàu đầu máy đơn","date":"2018-11-28","departedTime":"2018-11-27T18:05:00.000Z","arriveTime":"2018-11-27T19:00:00.000Z","company":"TCT","status":6},"locomotive":[{"type":"C","name":"D11H-357","fromStation":"Đà Nẵng","toStation":"Kim Liên","fromTime":"2018-11-27T18:05:00.000Z","toTime":"2018-11-27T19:00:00.000Z"}],"timetable":[{"station":"Đà Nẵng","out":"2018-11-27T18:05:00.000Z"},{"station":"Kim Liên","in":"2018-11-27T19:00:00.000Z"}]},{"info":{"fromStation":"Gia Lâm","toStation":"Yên Viên","name":"A9901","type":"Tàu thoi 1 khu gian, tàu công trình 1 khu gian","date":"2018-11-28","departedTime":"2018-11-27T18:00:00.000Z","arriveTime":"2018-11-27T18:10:00.000Z","company":"FRA","status":6},"locomotive":[{"type":"C","name":"D12E-655","fromStation":"Gia Lâm","toStation":"Yên Viên","fromTime":"2018-11-27T18:00:00.000Z","toTime":"2018-11-27T18:10:00.000Z"}],"timetable":[{"station":"Gia Lâm","out":"2018-11-27T18:00:00.000Z"},{"station":"Yên Viên","in":"2018-11-27T18:10:00.000Z"}]},{"info":{"fromStation":"Sóng Thần","toStation":"Giáp Bát","name":"AH2","type":"Tàu hàng chuyên tuyến","date":"2018-11-28","departedTime":"2018-11-27T17:51:00.000Z","arriveTime":"1970-01-01T00:00:00.000Z","company":"FRA","status":4},"locomotive":[{"type":"C","name":"D19E-918","fromStation":"Sóng Thần","toStation":"Trảng Bom","fromTime":"2018-11-27T17:51:00.000Z","toTime":"2018-11-27T20:02:00.000Z"}],"timetable":[{"station":"Sóng Thần","out":"2018-11-27T17:51:00.000Z"},{"station":"Hố Nai","in":"2018-11-27T18:36:00.000Z","out":"2018-11-27T20:01:00.000Z"},{"station":"Trảng Bom","in":"2018-11-27T20:02:00.000Z","out":"2018-11-27T21:54:00.000Z"}]},{"info":{"fromStation":"Phố Lu","toStation":"Lào Cai","name":"4731","type":"Tàu thoi nhiều khu gian, tàu công trình nhiều khu gian","date":"2018-11-28","departedTime":"2018-11-27T17:50:00.000Z","arriveTime":"2018-11-27T19:10:00.000Z","company":"FHN","status":6},"locomotive":[{"type":"C","name":"D10H-006","fromStation":"Phố Lu","toStation":"Lào Cai","fromTime":"2018-11-27T17:50:00.000Z","toTime":"2018-11-27T19:10:00.000Z"}],"timetable":[{"station":"Phố Lu","out":"2018-11-27T17:50:00.000Z"},{"station":"Lào Cai","in":"2018-11-27T19:10:00.000Z"}]},{"info":{"fromStation":"Hải Phòng","toStation":"Yên Viên","name":"9109/3108","type":"Tàu thoi 1 khu gian, tàu công trình 1 khu gian","date":"2018-11-28","departedTime":"2018-11-27T17:48:00.000Z","arriveTime":"2018-11-27T20:28:00.000Z","company":"FHN","status":6},"locomotive":[{"type":"C","name":"D19E-979","fromStation":"Hải Phòng","toStation":"Yên Viên","fromTime":"2018-11-27T17:48:00.000Z","toTime":"2018-11-27T20:28:00.000Z"}],"timetable":[{"station":"Hải Phòng","out":"2018-11-27T17:48:00.000Z"},{"station":"Thượng Lý","in":"2018-11-27T18:00:00.000Z","out":"2018-11-27T18:00:00.000Z"},{"station":"Vật Cách","in":"2018-11-27T18:09:00.000Z","out":"2018-11-27T18:09:00.000Z"},{"station":"Gia Lâm","in":"2018-11-27T20:16:00.000Z","out":"2018-11-27T20:16:00.000Z"},{"station":"Yên Viên","in":"2018-11-27T20:28:00.000Z"}]},{"info":{"fromStation":"Mạo Khê","toStation":"Cổ Thành","name":"54550","type":"Tàu thoi nhiều khu gian, tàu công trình nhiều khu gian","date":"2018-11-28","departedTime":"2018-11-27T17:45:00.000Z","arriveTime":"2018-11-27T19:18:00.000Z","company":"FHN","status":6},"locomotive":[{"type":"C","name":"D19Er-2032","fromStation":"Mạo Khê","toStation":"Cổ Thành","fromTime":"2018-11-27T17:45:00.000Z","toTime":"2018-11-27T19:18:00.000Z"}],"timetable":[{"station":"Mạo Khê","out":"2018-11-27T17:45:00.000Z"},{"station":"Chí Linh","in":"2018-11-27T18:45:18.000Z","out":"2018-11-27T18:45:18.000Z"},{"station":"Cổ Thành","in":"2018-11-27T19:18:00.000Z"}]},{"info":{"fromStation":"Thịnh Châu","toStation":"Phủ Lý","name":"9308","type":"Tàu thoi 1 khu gian, tàu công trình 1 khu gian","date":"2018-11-28","departedTime":"2018-11-27T17:33:26.000Z","arriveTime":"2018-11-27T17:49:00.000Z","company":"FHN","status":6},"locomotive":[{"type":"C","name":"D19E-910","fromStation":"Thịnh Châu","toStation":"Phủ Lý","fromTime":"2018-11-27T17:33:26.000Z","toTime":"2018-11-27T17:49:00.000Z"}],"timetable":[{"station":"Thịnh Châu","out":"2018-11-27T17:33:26.000Z"},{"station":"Phủ Lý","in":"2018-11-27T17:49:00.000Z"}]},{"info":{"fromStation":"Lào Cai","toStation":"Yên Viên","name":"A2214","type":"Tàu hàng khu đoạn","date":"2018-11-28","departedTime":"2018-11-27T17:30:00.000Z","arriveTime":"1970-01-01T00:00:00.000Z","company":"FRA","status":4},"locomotive":[{"type":"C","name":"D19E-974","fromStation":"Lào Cai","toStation":"Văn Phú","fromTime":"2018-11-27T17:30:00.000Z","toTime":"2018-11-27T23:47:00.000Z"}],"timetable":[{"station":"Lào Cai","out":"2018-11-27T17:30:00.000Z"},{"station":"Phố Lu","in":"2018-11-27T18:30:00.000Z","out":"2018-11-27T18:30:00.000Z"},{"station":"Lâm Giang","in":"2018-11-27T21:31:00.000Z","out":"2018-11-27T21:31:00.000Z"},{"station":"Yên Bái","in":"2018-11-27T23:12:00.000Z","out":"2018-11-27T23:32:00.000Z"},{"station":"Văn Phú","in":"2018-11-27T23:47:00.000Z","out":"2018-11-27T23:47:00.000Z"}]},{"info":{"fromStation":"Xuân Giao A","toStation":"Lâm Thao","name":"2748","type":"Tàu hàng khu đoạn","date":"2018-11-28","departedTime":"2018-11-27T17:27:00.000Z","arriveTime":"2018-11-28T01:06:00.000Z","company":"FHN","status":6},"locomotive":[{"type":"C","name":"D10H-027","fromStation":"Xuân Giao A","toStation":"Lâm Thao","fromTime":"2018-11-27T17:27:00.000Z","toTime":"2018-11-28T01:06:00.000Z"}],"timetable":[{"station":"Xuân Giao A","out":"2018-11-27T17:27:00.000Z"},{"station":"Phố Lu","in":"2018-11-27T17:55:00.000Z","out":"2018-11-27T17:55:00.000Z"},{"station":"Lâm Giang","in":"2018-11-27T19:54:00.000Z","out":"2018-11-27T20:07:00.000Z"},{"station":"Yên Bái","in":"2018-11-27T22:00:00.000Z","out":"2018-11-27T22:45:00.000Z"},{"station":"Văn Phú","in":"2018-11-27T23:01:00.000Z","out":"2018-11-27T23:01:00.000Z"},{"station":"Tiên Kiên","in":"2018-11-28T00:54:00.000Z","out":"2018-11-28T00:54:00.000Z"},{"station":"Lâm Thao","in":"2018-11-28T01:06:00.000Z"}]},{"info":{"fromStation":"Hải Phòng","toStation":"Yên Viên","name":"9111/3110","type":"Tàu thoi 1 khu gian, tàu công trình 1 khu gian","date":"2018-11-28","departedTime":"2018-11-27T17:25:00.000Z","arriveTime":"2018-11-27T23:30:00.000Z","company":"FHN","status":6},"locomotive":[{"type":"C","name":"D19E-965","fromStation":"Hải Phòng","toStation":"Yên Viên","fromTime":"2018-11-27T17:25:00.000Z","toTime":"2018-11-27T23:30:00.000Z"}],"timetable":[{"station":"Hải Phòng","out":"2018-11-27T17:25:00.000Z"},{"station":"Thượng Lý","in":"2018-11-27T17:36:00.000Z","out":"2018-11-27T17:36:00.000Z"},{"station":"Vật Cách","in":"2018-11-27T17:50:00.000Z","out":"2018-11-27T20:19:00.000Z"},{"station":"Gia Lâm","in":"2018-11-27T23:14:00.000Z","out":"2018-11-27T23:14:00.000Z"},{"station":"Yên Viên","in":"2018-11-27T23:30:00.000Z"}]},{"info":{"fromStation":"Giáp Bát","toStation":"Sóng Thần","name":"HH5","type":"Tàu hàng chuyên tuyến","date":"2018-11-28","departedTime":"2018-11-27T17:08:00.000Z","arriveTime":"1970-01-01T00:00:00.000Z","company":"FHN","status":4},"locomotive":[{"type":"C","name":"D19E-904","fromStation":"Giáp Bát","toStation":"Hoàng Mai","fromTime":"2018-11-27T17:08:00.000Z","toTime":"2018-11-28T00:18:00.000Z"}],"timetable":[{"station":"Giáp Bát","out":"2018-11-27T17:08:00.000Z"},{"station":"Văn Điển","in":"2018-11-27T17:17:00.000Z","out":"2018-11-27T17:17:00.000Z"},{"station":"Phủ Lý","in":"2018-11-27T18:19:00.000Z","out":"2018-11-27T18:19:00.000Z"},{"station":"Ninh Bình","in":"2018-11-27T20:17:00.000Z","out":"2018-11-27T20:17:00.000Z"},{"station":"Cầu Yên","in":"2018-11-27T20:24:00.000Z","out":"2018-11-27T20:24:00.000Z"},{"station":"Bỉm Sơn","in":"2018-11-27T20:59:00.000Z","out":"2018-11-27T20:59:00.000Z"},{"station":"Thanh Hóa","in":"2018-11-27T22:03:00.000Z","out":"2018-11-27T22:08:00.000Z"},{"station":"Yên Thái","in":"2018-11-27T22:24:00.000Z","out":"2018-11-27T22:24:00.000Z"},{"station":"Trường Lâm","in":"2018-11-28T00:00:00.000Z","out":"2018-11-28T00:06:00.000Z"},{"station":"Hoàng Mai","in":"2018-11-28T00:18:00.000Z","out":"2018-11-28T00:18:00.000Z"}]},{"info":{"fromStation":"Đà Nẵng","toStation":"Kim Liên","name":"0404","type":"Tàu đầu máy đơn","date":"2018-11-28","departedTime":"2018-11-27T17:05:00.000Z","arriveTime":"2018-11-27T17:19:00.000Z","company":"TCT","status":6},"locomotive":[{"type":"C","name":"D20E-014","fromStation":"Đà Nẵng","toStation":"Kim Liên","fromTime":"2018-11-27T17:05:00.000Z","toTime":"2018-11-27T17:19:00.000Z"}],"timetable":[{"station":"Đà Nẵng","out":"2018-11-27T17:05:00.000Z"},{"station":"Kim Liên","in":"2018-11-27T17:19:00.000Z"}]}]